[{"coords": [0, 0], "value": [2], "names": ["tj02pj00"]}, {"coords": [0, 1], "value": [1, 1], "names": ["glassar", "lucasdow1"]}, {"coords": [0, 2], "value": [2], "names": ["glassar"]}, {"coords": [0, 3], "value": [5, 1], "names": ["glassar", "lucasdow1"]}, {"coords": [0, 4], "value": [2, 2], "names": ["metaAgi", "glassar"]}, {"coords": [0, 5], "value": [1, 2, 1], "names": ["JoelAuni", "tj02pj00", "sfkwww"]}, {"coords": [0, 6], "value": [1, 1, 1, 3, 2, 1, 1], "names": ["JoelAuni", "tj02pj00", "metaAgi", "marresaurus", "Zeffiii", "NuppeNoo", "Tina_T"]}, {"coords": [0, 7], "value": [1, 3, 7, 3, 3, 7], "names": ["Jerua", "tj02pj00", "marresaurus", "Zeffiii", "NuppeNoo", "Tina_T"]}, {"coords": [0, 8], "value": [3, 1, 3, 1, 2, 3], "names": ["Jerua", "tj02pj00", "marresaurus", "Zeffiii", "NuppeNoo", "Tina_T"]}, {"coords": [0, 9], "value": [7, 1, 5], "names": ["Jerua", "Leddy231", "marresaurus"]}, {"coords": [0, 10], "value": [1], "names": ["Jerua"]}, {"coords": [0, 11], "value": [], "names": []}, {"coords": [0, 12], "value": [], "names": []}, {"coords": [0, 13], "value": [1], "names": ["METALeddy231"]}, {"coords": [0, 14], "value": [2, 1], "names": ["_gabben", "METALeddy231"]}, {"coords": [0, 15], "value": [2, 2], "names": ["_gabben", "METALeddy231"]}, {"coords": [1, 0], "value": [1], "names": ["tj02pj00"]}, {"coords": [1, 1], "value": [1], "names": ["tj02pj00"]}, {"coords": [1, 2], "value": [1, 1], "names": ["tj02pj00", "glassar"]}, {"coords": [1, 3], "value": [1, 1], "names": ["tj02pj00", "glassar"]}, {"coords": [1, 4], "value": [3, 2, 3, 1], "names": ["Twosai2", "tj02pj00", "metaAgi", "NuppeNoo"]}, {"coords": [1, 5], "value": [5, 1, 4, 1, 4], "names": ["Twosai2", "tj02pj00", "metaAgi", "sfkwww", "NuppeNoo"]}, {"coords": [1, 6], "value": [2, 2, 3, 1], "names": ["metaAgi", "Zeffiii", "NuppeNoo", "Tina_T"]}, {"coords": [1, 7], "value": [1, 3, 2, 2, 2, 2], "names": ["Jerua", "tj02pj00", "marresaurus", "Zeffiii", "NuppeNoo", "Tina_T"]}, {"coords": [1, 8], "value": [3, 3, 1, 4, 2], "names": ["Jerua", "Leddy231", "tj02pj00", "marresaurus", "NuppeNoo"]}, {"coords": [1, 9], "value": [2, 8], "names": ["Leddy231", "marresaurus"]}, {"coords": [1, 10], "value": [2, 2], "names": ["marresaurus", "METALeddy231"]}, {"coords": [1, 11], "value": [8], "names": ["METALeddy231"]}, {"coords": [1, 12], "value": [4], "names": ["METALeddy231"]}, {"coords": [1, 13], "value": [17], "names": ["METALeddy231"]}, {"coords": [1, 14], "value": [1, 4], "names": ["_gabben", "METALeddy231"]}, {"coords": [1, 15], "value": [2, 1], "names": ["METALeddy231", "METAknekt"]}, {"coords": [2, 0], "value": [], "names": []}, {"coords": [2, 1], "value": [], "names": []}, {"coords": [2, 2], "value": [1, 1], "names": ["Twosai2", "glassar"]}, {"coords": [2, 3], "value": [1, 1, 2, 1], "names": ["Twosai2", "sfkwww", "NuppeNoo", "glassar"]}, {"coords": [2, 4], "value": [1, 1, 3, 1], "names": ["Twosai2", "metaAgi", "NuppeNoo", "Blytung"]}, {"coords": [2, 5], "value": [1, 2, 2, 2, 1, 3, 2], "names": ["Kevdras", "Twosai2", "metaAgi", "sfkwww", "Zeffiii", "NuppeNoo", "Blytung"]}, {"coords": [2, 6], "value": [4, 2, 3, 1], "names": ["metaAgi", "Zeffiii", "NuppeNoo", "Blytung"]}, {"coords": [2, 7], "value": [3, 2, 1, 7, 1], "names": ["tj02pj00", "c0n7us3d", "Zeffiii", "NuppeNoo", "Tina_T"]}, {"coords": [2, 8], "value": [1, 2, 4, 4, 1, 3, 6, 1], "names": ["Jerua", "Leddy231", "tj02pj00", "marresaurus", "wokki10", "METALeddy231", "NuppeNoo", "Tina_T"]}, {"coords": [2, 9], "value": [1, 1, 3, 1, 5], "names": ["Leddy231", "tj02pj00", "marresaurus", "METALeddy231", "NuppeNoo"]}, {"coords": [2, 10], "value": [1, 1, 1], "names": ["c0n7us3d", "METALeddy231", "NuppeNoo"]}, {"coords": [2, 11], "value": [2, 2, 1], "names": ["c0n7us3d", "METALeddy231", "METAknekt"]}, {"coords": [2, 12], "value": [2, 3, 1], "names": ["c0n7us3d", "METALeddy231", "METAknekt"]}, {"coords": [2, 13], "value": [3, 3], "names": ["METALeddy231", "METAknekt"]}, {"coords": [2, 14], "value": [1, 7], "names": ["METALeddy231", "METAknekt"]}, {"coords": [2, 15], "value": [1, 2], "names": ["METALeddy231", "METAknekt"]}, {"coords": [3, 0], "value": [1], "names": ["Twosai2"]}, {"coords": [3, 1], "value": [1, 1], "names": ["Twosai2", "metaAgi"]}, {"coords": [3, 2], "value": [2, 2, 1], "names": ["Twosai2", "metaAgi", "sfkwww"]}, {"coords": [3, 3], "value": [2, 4, 5, 2], "names": ["Twosai2", "metaAgi", "sfkwww", "glassar"]}, {"coords": [3, 4], "value": [5, 6, 4, 1, 1, 2, 3], "names": ["Twosai2", "metaAgi", "sfkwww", "Zeffiii", "NuppeNoo", "glassar", "Blytung"]}, {"coords": [3, 5], "value": [5, 5, 1, 1, 2, 5, 3, 1, 7], "names": ["Kevdras", "Twosai2", "Leddy231", "metaAgi", "sfkwww", "Zeffiii", "NuppeNoo", "glassar", "Blytung"]}, {"coords": [3, 6], "value": [5, 3, 1, 2, 2, 1, 3], "names": ["Kevdras", "Killgon", "Leddy231", "metaAgi", "Zeffiii", "NuppeNoo", "Blytung"]}, {"coords": [3, 7], "value": [1, 4, 1, 1, 3, 1, 3, 3], "names": ["Kevdras", "Killgon", "Leddy231", "tj02pj00", "c0n7us3d", "Zeffiii", "NuppeNoo", "Tina_T"]}, {"coords": [3, 8], "value": [1, 2, 4, 2, 2, 2, 3], "names": ["tj02pj00", "c0n7us3d", "marresaurus", "wokki10", "METALeddy231", "NuppeNoo", "Tina_T"]}, {"coords": [3, 9], "value": [1, 2, 1, 2, 1, 3, 6, 1], "names": ["aggyagnesagi", "Leddy231", "tj02pj00", "marresaurus", "wokki10", "METALeddy231", "NuppeNoo", "Tina_T"]}, {"coords": [3, 10], "value": [3, 5, 1, 3, 3, 4, 1], "names": ["aggyagnesagi", "Leddy231", "c0n7us3d", "marresaurus", "METALeddy231", "NuppeNoo", "METAknekt"]}, {"coords": [3, 11], "value": [3, 3, 2, 3, 3], "names": ["Leddy231", "c0n7us3d", "marresaurus", "NuppeNoo", "METAknekt"]}, {"coords": [3, 12], "value": [1, 3, 1, 2], "names": ["Leddy231", "c0n7us3d", "marresaurus", "METAknekt"]}, {"coords": [3, 13], "value": [1, 1], "names": ["marresaurus", "METAknekt"]}, {"coords": [3, 14], "value": [3, 5], "names": ["METALeddy231", "METAknekt"]}, {"coords": [3, 15], "value": [1, 1], "names": ["METALeddy231", "METAknekt"]}, {"coords": [4, 0], "value": [1], "names": ["Twosai2"]}, {"coords": [4, 1], "value": [], "names": []}, {"coords": [4, 2], "value": [], "names": []}, {"coords": [4, 3], "value": [2, 1], "names": ["metaAgi", "glassar"]}, {"coords": [4, 4], "value": [2, 1, 5, 6, 1, 1, 1, 1, 1], "names": ["Kevdras", "Killgon", "Twosai2", "metaAgi", "sfkwww", "Zeffiii", "NuppeNoo", "glassar", "Blytung"]}, {"coords": [4, 5], "value": [11, 1, 5, 1, 1, 7, 3, 1, 5], "names": ["Kevdras", "Killgon", "Twosai2", "Leddy231", "sfkwww", "Zeffiii", "NuppeNoo", "glassar", "Blytung"]}, {"coords": [4, 6], "value": [10, 3, 6, 1, 1, 1, 2, 8], "names": ["Kevdras", "Killgon", "Leddy231", "metaAgi", "Zeffiii", "NuppeNoo", "Tina_T", "Blytung"]}, {"coords": [4, 7], "value": [4, 4, 5, 1, 1, 2, 2, 1, 1, 6, 3], "names": ["Kevdras", "Killgon", "Leddy231", "tj02pj00", "c0n7us3d", "metaAgi", "wokki10", "METALeddy231", "NuppeNoo", "Tina_T", "Blytung"]}, {"coords": [4, 8], "value": [1, 1, 1, 3, 3, 1, 1, 3, 1, 3], "names": ["Kevdras", "Killgon", "tj02pj00", "c0n7us3d", "metaAgi", "marresaurus", "wokki10", "METALeddy231", "glassar", "Tina_T"]}, {"coords": [4, 9], "value": [1, 5, 3, 1, 2, 2, 1, 1], "names": ["Leddy231", "tj02pj00", "c0n7us3d", "marresaurus", "METALeddy231", "NuppeNoo", "METAknekt", "Tina_T"]}, {"coords": [4, 10], "value": [7, 2, 3, 13, 4, 1], "names": ["aggyagnesagi", "Leddy231", "tj02pj00", "c0n7us3d", "marresaurus", "METAknekt"]}, {"coords": [4, 11], "value": [1, 4, 8, 4, 3, 5], "names": ["aggyagnesagi", "Leddy231", "c0n7us3d", "marresaurus", "NuppeNoo", "METAknekt"]}, {"coords": [4, 12], "value": [2, 9, 4, 1, 2], "names": ["Leddy231", "c0n7us3d", "marresaurus", "NuppeNoo", "METAknekt"]}, {"coords": [4, 13], "value": [2, 2, 2], "names": ["Twosai2", "marresaurus", "METAknekt"]}, {"coords": [4, 14], "value": [4], "names": ["Twosai2"]}, {"coords": [4, 15], "value": [1], "names": ["Twosai2"]}, {"coords": [5, 0], "value": [3], "names": ["SofiaTilde"]}, {"coords": [5, 1], "value": [], "names": []}, {"coords": [5, 2], "value": [1], "names": ["Zeffiii"]}, {"coords": [5, 3], "value": [3, 1, 1, 1], "names": ["Killgon", "Zeffiii", "glassar", "metaNosh"]}, {"coords": [5, 4], "value": [1, 7, 3, 1, 4, 1, 1, 2, 1], "names": ["Kevdras", "Killgon", "Twosai2", "metaAgi", "sfkwww", "Zeffiii", "NuppeNoo", "glassar", "metaNosh"]}, {"coords": [5, 5], "value": [4, 3, 2, 1, 1, 3, 2, 3, 5, 4], "names": ["Kevdras", "Killgon", "Twosai2", "Leddy231", "sfkwww", "Zeffiii", "NuppeNoo", "glassar", "Blytung", "metaNosh"]}, {"coords": [5, 6], "value": [3, 4, 3, 2, 1, 1, 2, 9, 6], "names": ["Kevdras", "Killgon", "Leddy231", "c0n7us3d", "Zeffiii", "METAknekt", "glassar", "Blytung", "metaNosh"]}, {"coords": [5, 7], "value": [7, 4, 1, 1, 2, 2, 1, 8, 2, 2, 1, 1, 4, 8, 4], "names": ["Kevdras", "Killgon", "Leddy231", "tj02pj00", "c0n7us3d", "metaAgi", "marresaurus", "wokki10", "METALeddy231", "METAknekt", "glassar", "Tina_T", "SofiaTilde2", "Blytung", "metaNosh"]}, {"coords": [5, 8], "value": [4, 1, 1, 2, 2, 2, 3, 3, 3, 1, 3, 3], "names": ["Kevdras", "Twosai2", "Leddy231", "c0n7us3d", "metaAgi", "marresaurus", "wokki10", "METAknekt", "glassar", "Tina_T", "SofiaTilde2", "Blytung"]}, {"coords": [5, 9], "value": [4, 1, 2, 2, 4, 2, 1, 1], "names": ["Twosai2", "Leddy231", "tj02pj00", "NuppeNoo", "METAknekt", "glassar", "Tina_T", "metaNosh"]}, {"coords": [5, 10], "value": [1, 1, 1, 4, 7, 1, 3, 1], "names": ["aggyagnesagi", "Twosai2", "Leddy231", "tj02pj00", "c0n7us3d", "NuppeNoo", "METAknekt", "Tina_T"]}, {"coords": [5, 11], "value": [1, 2, 8, 3, 4, 1, 6], "names": ["aggyagnesagi", "Twosai2", "Leddy231", "c0n7us3d", "SofiaTilde", "NuppeNoo", "METAknekt"]}, {"coords": [5, 12], "value": [1, 7, 2, 9, 2, 4, 1], "names": ["aggyagnesagi", "Twosai2", "Leddy231", "c0n7us3d", "marresaurus", "SofiaTilde", "METAknekt"]}, {"coords": [5, 13], "value": [2, 4, 1, 1, 3], "names": ["aggyagnesagi", "Twosai2", "c0n7us3d", "marresaurus", "SofiaTilde"]}, {"coords": [5, 14], "value": [1], "names": ["Twosai2"]}, {"coords": [5, 15], "value": [3], "names": ["SofiaTilde"]}, {"coords": [6, 0], "value": [1, 1, 1], "names": ["BaraEllinor", "SofiaTilde", "Zeffiii"]}, {"coords": [6, 1], "value": [1, 2], "names": ["BaraEllinor", "Zeffiii"]}, {"coords": [6, 2], "value": [3, 1], "names": ["BaraEllinor", "Zeffiii"]}, {"coords": [6, 3], "value": [1, 1, 1], "names": ["glas464", "glassar", "metaNosh"]}, {"coords": [6, 4], "value": [2, 2, 1, 3, 1, 4], "names": ["Killgon", "metaAgi", "sfkwww", "glas464", "Blytung", "metaNosh"]}, {"coords": [6, 5], "value": [1, 1, 4, 1, 2, 2, 3, 6], "names": ["Kevdras", "Leddy231", "metaAgi", "NuppeNoo", "glas464", "glassar", "Blytung", "metaNosh"]}, {"coords": [6, 6], "value": [1, 1, 1, 1, 5, 1, 2, 6, 5], "names": ["Kevdras", "Killgon", "Leddy231", "c0n7us3d", "metaAgi", "wokki10", "glassar", "Blytung", "metaNosh"]}, {"coords": [6, 7], "value": [5, 2, 1, 1, 4, 1, 1, 3, 4, 2, 1, 1, 2, 3, 4], "names": ["Kevdras", "Killgon", "tj02pj00", "c0n7us3d", "metaAgi", "sfkwww", "marresaurus", "wokki10", "METALeddy231", "glas464", "glassar", "Tina_T", "SofiaTilde2", "Blytung", "metaNosh"]}, {"coords": [6, 8], "value": [2, 3, 2, 1, 2, 1, 1, 1, 1, 1, 3, 3, 2, 2, 2], "names": ["BaraEllinor", "Kevdras", "Twosai2", "tj02pj00", "c0n7us3d", "metaAgi", "SofiaTilde", "METALeddy231", "METAknekt", "glas464", "glassar", "Tina_T", "SofiaTilde2", "Blytung", "metaNosh"]}, {"coords": [6, 9], "value": [4, 3, 1, 1, 2, 2, 3, 3], "names": ["Twosai2", "tj02pj00", "metaAgi", "wokki10", "NuppeNoo", "glassar", "Tina_T", "metaNosh"]}, {"coords": [6, 10], "value": [1, 4, 1, 1, 1, 2, 2, 2, 3], "names": ["Leddy231", "tj02pj00", "c0n7us3d", "SofiaTilde", "NuppeNoo", "METAknekt", "glas464", "Tina_T", "metaNosh"]}, {"coords": [6, 11], "value": [1, 2, 5, 3, 2, 1, 1], "names": ["aggyagnesagi", "Twosai2", "Leddy231", "SofiaTilde", "METAknekt", "glas464", "metaNosh"]}, {"coords": [6, 12], "value": [4, 1, 3, 2], "names": ["Twosai2", "Leddy231", "SofiaTilde", "METAknekt"]}, {"coords": [6, 13], "value": [1, 4, 2], "names": ["aggyagnesagi", "Twosai2", "SofiaTilde"]}, {"coords": [6, 14], "value": [2, 2], "names": ["SofiaTilde", "Zeffiii"]}, {"coords": [6, 15], "value": [1, 4, 4], "names": ["BaraEllinor", "SofiaTilde", "Zeffiii"]}, {"coords": [7, 0], "value": [3], "names": ["SofiaTilde"]}, {"coords": [7, 1], "value": [5, 3], "names": ["SofiaTilde", "Zeffiii"]}, {"coords": [7, 2], "value": [3, 6, 2, 5, 1], "names": ["BaraEllinor", "SofiaTilde", "Zeffiii", "glas464", "SofiaTilde2"]}, {"coords": [7, 3], "value": [1, 3, 8, 5, 2], "names": ["BaraEllinor", "SofiaTilde", "glas464", "glassar", "metaNosh"]}, {"coords": [7, 4], "value": [2, 2, 1, 1, 10, 1, 1, 3], "names": ["Killgon", "sfkwww", "SofiaTilde", "NuppeNoo", "glas464", "glassar", "Blytung", "metaNosh"]}, {"coords": [7, 5], "value": [1, 2, 3, 2, 3, 5, 3, 6], "names": ["Leddy231", "metaAgi", "sfkwww", "SofiaTilde", "NuppeNoo", "glas464", "Blytung", "metaNosh"]}, {"coords": [7, 6], "value": [2, 2, 1, 2, 1, 6, 3, 1, 2, 1, 2, 2, 3, 10], "names": ["BaraEllinor", "Kevdras", "Killgon", "KrukPorr", "Leddy231", "metaAgi", "sfkwww", "wokki10", "SofiaTilde", "METALeddy231", "glas464", "glassar", "Blytung", "metaNosh"]}, {"coords": [7, 7], "value": [1, 4, 2, 2, 3, 1, 7, 6, 1, 7, 1, 1, 3, 2, 1, 1, 1, 4], "names": ["BaraEllinor", "Kevdras", "Killgon", "KrukPorr", "Leddy231", "c0n7us3d", "metaAgi", "sfkwww", "marresaurus", "wokki10", "SofiaTilde", "METALeddy231", "glas464", "glassar", "Tina_T", "SofiaTilde2", "Blytung", "metaNosh"]}, {"coords": [7, 8], "value": [2, 6, 1, 1, 2, 2, 1, 2, 4, 3, 4, 1, 5, 4, 1, 1, 6, 2, 3, 5, 2, 3, 1], "names": ["BaraEllinor", "Kevdras", "aggyagnesagi", "Jerua", "Twosai2", "KrukPorr", "JoelAuni", "tj02pj00", "c0n7us3d", "metaAgi", "sfkwww", "marresaurus", "wokki10", "SofiaTilde", "_gabben", "NuppeNoo", "METAknekt", "glas464", "glassar", "Tina_T", "SofiaTilde2", "Blytung", "metaNosh"]}, {"coords": [7, 9], "value": [4, 1, 1, 1, 2, 4, 3, 3, 6, 1, 1, 5, 1, 3, 2, 1], "names": ["Kevdras", "aggyagnesagi", "Twosai2", "KrukPorr", "JoelAuni", "tj02pj00", "c0n7us3d", "metaAgi", "wokki10", "NuppeNoo", "METAknekt", "glas464", "glassar", "Tina_T", "SofiaTilde2", "Blytung"]}, {"coords": [7, 10], "value": [4, 2, 3, 1, 1, 2, 2, 1, 2], "names": ["tj02pj00", "c0n7us3d", "wokki10", "SofiaTilde", "METAknekt", "glas464", "Tina_T", "SofiaTilde2", "metaNosh"]}, {"coords": [7, 11], "value": [5, 1, 2], "names": ["aggyagnesagi", "tj02pj00", "SofiaTilde"]}, {"coords": [7, 12], "value": [1, 2, 2, 1, 2, 1], "names": ["BaraEllinor", "aggyagnesagi", "Twosai2", "SofiaTilde", "Zeffiii", "METAknekt"]}, {"coords": [7, 13], "value": [1, 5, 2], "names": ["BaraEllinor", "aggyagnesagi", "Zeffiii"]}, {"coords": [7, 14], "value": [2, 2, 2], "names": ["BaraEllinor", "aggyagnesagi", "Zeffiii"]}, {"coords": [7, 15], "value": [1, 3, 2], "names": ["BaraEllinor", "SofiaTilde", "Zeffiii"]}, {"coords": [8, 0], "value": [5, 2], "names": ["SofiaTilde", "SofiaTilde2"]}, {"coords": [8, 1], "value": [4, 2], "names": ["SofiaTilde", "SofiaTilde2"]}, {"coords": [8, 2], "value": [2, 6, 3], "names": ["BaraEllinor", "glas464", "SofiaTilde2"]}, {"coords": [8, 3], "value": [2, 1, 8, 3], "names": ["BaraEllinor", "SofiaTilde", "glas464", "glassar"]}, {"coords": [8, 4], "value": [1, 3, 2, 1, 3, 3], "names": ["BaraEllinor", "Killgon", "Leddy231", "sfkwww", "glas464", "Blytung"]}, {"coords": [8, 5], "value": [1, 2, 4, 3, 2, 7, 2], "names": ["Killgon", "Leddy231", "sfkwww", "glas464", "glassar", "Blytung", "metaNosh"]}, {"coords": [8, 6], "value": [3, 2, 2, 3, 6, 1, 1, 2, 1, 2, 2, 1, 7], "names": ["BaraEllinor", "Killgon", "JoelAuni", "Leddy231", "sfkwww", "Effa", "wokki10", "glas444", "METALeddy231", "glas464", "glassar", "Tina_T", "metaNosh"]}, {"coords": [8, 7], "value": [3, 4, 3, 2, 1, 2, 1, 4, 5, 1, 5, 1, 1, 1, 2, 3, 2, 1, 5, 1], "names": ["BaraEllinor", "Kevdras", "Killgon", "Twosai2", "KrukPorr", "JoelAuni", "isahas", "Leddy231", "sfkwww", "Effa", "wokki10", "glas444", "METALeddy231", "METAknekt", "glas464", "glassar", "Tina_T", "Blytung", "metaNosh", "CornetTheBunny"]}, {"coords": [8, 8], "value": [2, 4, 3, 4, 1, 1, 5, 2, 2, 1, 3, 5, 10, 1, 1, 5, 8, 2, 1, 5, 2, 1, 3, 1], "names": ["BaraEllinor", "Kevdras", "Jerua", "Killgon", "Twosai2", "KrukPorr", "JoelAuni", "isahas", "tj02pj00", "c0n7us3d", "metaAgi", "sfkwww", "wokki10", "SofiaTilde", "Zeffiii", "_gabben", "METAknekt", "glas464", "glassar", "Tina_T", "SofiaTilde2", "Blytung", "metaNosh", "lucasdow1"]}, {"coords": [8, 9], "value": [5, 6, 1, 3, 3, 1, 4, 1, 2, 1, 2, 4, 3, 5, 7, 1, 1, 2], "names": ["Kevdras", "aggyagnesagi", "Jerua", "Killgon", "JoelAuni", "isahas", "tj02pj00", "c0n7us3d", "metaAgi", "sfkwww", "wokki10", "Zeffiii", "_gabben", "METAknekt", "glas464", "SofiaTilde2", "Blytung", "metaNosh"]}, {"coords": [8, 10], "value": [4, 1, 6, 1, 1, 1, 7, 1, 1, 2, 2], "names": ["aggyagnesagi", "isahas", "tj02pj00", "c0n7us3d", "wokki10", "SofiaTilde", "_gabben", "METAknekt", "glas464", "SofiaTilde2", "metaNosh"]}, {"coords": [8, 11], "value": [5, 2, 1, 1, 4, 2], "names": ["aggyagnesagi", "isahas", "wokki10", "SofiaTilde", "_gabben", "SofiaTilde2"]}, {"coords": [8, 12], "value": [1, 5, 1, 1, 1, 2], "names": ["BaraEllinor", "aggyagnesagi", "isahas", "SofiaTilde", "Zeffiii", "SofiaTilde2"]}, {"coords": [8, 13], "value": [1, 2], "names": ["BaraEllinor", "aggyagnesagi"]}, {"coords": [8, 14], "value": [1], "names": ["BaraEllinor"]}, {"coords": [8, 15], "value": [1, 2], "names": ["BaraEllinor", "SofiaTilde"]}, {"coords": [9, 0], "value": [2], "names": ["SofiaTilde2"]}, {"coords": [9, 1], "value": [1, 2, 5], "names": ["KrukPorr", "SofiaTilde", "SofiaTilde2"]}, {"coords": [9, 2], "value": [1, 2, 1, 3], "names": ["KrukPorr", "JoelAuni", "glas464", "SofiaTilde2"]}, {"coords": [9, 3], "value": [1, 3, 2, 1, 4, 2], "names": ["Killgon", "KrukPorr", "JoelAuni", "Leddy231", "glas464", "glassar"]}, {"coords": [9, 4], "value": [1, 2, 1, 5, 1, 3, 3], "names": ["BaraEllinor", "Killgon", "KrukPorr", "Leddy231", "Effa", "glas464", "glassar"]}, {"coords": [9, 5], "value": [1, 3, 3, 1, 5, 1, 1, 1, 1, 1], "names": ["BaraEllinor", "Killgon", "Leddy231", "sfkwww", "Effa", "wokki10", "glas464", "glassar", "Blytung", "metaNosh"]}, {"coords": [9, 6], "value": [6, 1, 3, 1, 1, 1, 2, 1, 1, 3], "names": ["BaraEllinor", "Killgon", "JoelAuni", "Leddy231", "sfkwww", "Effa", "wokki10", "glas444", "glas464", "metaNosh"]}, {"coords": [9, 7], "value": [4, 1, 2, 1, 2, 1, 2, 1, 4, 1, 2], "names": ["BaraEllinor", "Jerua", "Killgon", "JoelAuni", "isahas", "metaAgi", "wokki10", "glas444", "METAknekt", "SofiaTilde2", "CornetTheBunny"]}, {"coords": [9, 8], "value": [1, 3, 2, 1, 3, 2, 5, 2, 1, 5, 3, 1, 3, 5, 3, 3, 1, 1], "names": ["aggyagnesagi", "Jerua", "Killgon", "KrukPorr", "JoelAuni", "isahas", "tj02pj00", "metaAgi", "sfkwww", "wokki10", "glas444", "SofiaTilde", "Zeffiii", "_gabben", "METAknekt", "SofiaTilde2", "metaNosh", "lucasdow1"]}, {"coords": [9, 9], "value": [2, 6, 1, 2, 3, 3, 6, 2, 3, 2, 4, 5, 2, 1, 2], "names": ["Kevdras", "aggyagnesagi", "Jerua", "Killgon", "JoelAuni", "isahas", "tj02pj00", "Effa", "wokki10", "glas444", "Zeffiii", "_gabben", "METAknekt", "glas464", "SofiaTilde2"]}, {"coords": [9, 10], "value": [2, 2, 4, 3, 4, 3], "names": ["aggyagnesagi", "isahas", "tj02pj00", "Effa", "wokki10", "_gabben"]}, {"coords": [9, 11], "value": [2, 5, 2, 1, 1, 1, 3, 3], "names": ["BaraEllinor", "aggyagnesagi", "isahas", "tj02pj00", "wokki10", "SofiaTilde", "_gabben", "SofiaTilde2"]}, {"coords": [9, 12], "value": [2, 2, 1, 1, 1, 1, 1], "names": ["BaraEllinor", "aggyagnesagi", "isahas", "wokki10", "SofiaTilde", "_gabben", "SofiaTilde2"]}, {"coords": [9, 13], "value": [2, 1], "names": ["BaraEllinor", "aggyagnesagi"]}, {"coords": [9, 14], "value": [4], "names": ["BaraEllinor"]}, {"coords": [9, 15], "value": [3], "names": ["BaraEllinor"]}, {"coords": [10, 0], "value": [2, 1, 1], "names": ["KrukPorr", "JoelAuni", "CornetTheBunny"]}, {"coords": [10, 1], "value": [1, 1, 1, 2, 1, 1], "names": ["BaraEllinor", "KrukPorr", "SofiaTilde", "SofiaTilde2", "CornetTheBunny", "lucasdow1"]}, {"coords": [10, 2], "value": [1, 1, 3, 1, 3], "names": ["BaraEllinor", "JoelAuni", "SofiaTilde2", "CornetTheBunny", "lucasdow1"]}, {"coords": [10, 3], "value": [2, 1, 1, 1, 3, 1, 1], "names": ["BaraEllinor", "Killgon", "KrukPorr", "JoelAuni", "Effa", "SofiaTilde2", "CornetTheBunny"]}, {"coords": [10, 4], "value": [2, 1, 4, 1, 1, 3], "names": ["BaraEllinor", "JoelAuni", "Effa", "glas464", "glassar", "CornetTheBunny"]}, {"coords": [10, 5], "value": [1, 2, 5, 2, 3, 1, 1], "names": ["BaraEllinor", "Killgon", "JoelAuni", "Leddy231", "Effa", "glas444", "CornetTheBunny"]}, {"coords": [10, 6], "value": [2, 2, 2, 4, 3, 1, 4, 1], "names": ["BaraEllinor", "Jerua", "Killgon", "JoelAuni", "Effa", "wokki10", "glas444", "CornetTheBunny"]}, {"coords": [10, 7], "value": [3, 3, 2, 1, 1, 1, 1, 1, 3], "names": ["Jerua", "Killgon", "JoelAuni", "Effa", "wokki10", "glas444", "Zeffiii", "METAknekt", "CornetTheBunny"]}, {"coords": [10, 8], "value": [1, 2, 1, 1, 2, 2, 2, 2, 4, 3, 2, 1, 2, 1], "names": ["aggyagnesagi", "Jerua", "Killgon", "KrukPorr", "JoelAuni", "isahas", "tj02pj00", "wokki10", "glas444", "Zeffiii", "_gabben", "SofiaTilde2", "CornetTheBunny", "lucasdow1"]}, {"coords": [10, 9], "value": [2, 1, 1, 1, 7, 2, 1, 1, 4, 1, 5], "names": ["aggyagnesagi", "Jerua", "Killgon", "JoelAuni", "isahas", "tj02pj00", "Effa", "glas444", "Zeffiii", "_gabben", "SofiaTilde2"]}, {"coords": [10, 10], "value": [1, 5, 2, 1, 2], "names": ["isahas", "Effa", "wokki10", "glas444", "SofiaTilde2"]}, {"coords": [10, 11], "value": [2, 7, 2, 5, 2], "names": ["BaraEllinor", "aggyagnesagi", "isahas", "Effa", "SofiaTilde2"]}, {"coords": [10, 12], "value": [2, 6, 3, 1, 2], "names": ["BaraEllinor", "aggyagnesagi", "isahas", "wokki10", "_gabben"]}, {"coords": [10, 13], "value": [1, 3, 4, 1], "names": ["BaraEllinor", "aggyagnesagi", "isahas", "_gabben"]}, {"coords": [10, 14], "value": [1, 2], "names": ["BaraEllinor", "isahas"]}, {"coords": [10, 15], "value": [2], "names": ["BaraEllinor"]}, {"coords": [11, 0], "value": [1, 5, 2, 2], "names": ["KrukPorr", "JoelAuni", "CornetTheBunny", "lucasdow1"]}, {"coords": [11, 1], "value": [1, 1, 5, 5], "names": ["BaraEllinor", "JoelAuni", "CornetTheBunny", "lucasdow1"]}, {"coords": [11, 2], "value": [1, 5, 4], "names": ["JoelAuni", "CornetTheBunny", "lucasdow1"]}, {"coords": [11, 3], "value": [2, 1, 1, 1, 1, 1], "names": ["BaraEllinor", "Killgon", "KrukPorr", "Effa", "SofiaTilde2", "lucasdow1"]}, {"coords": [11, 4], "value": [4, 1, 1, 3, 1, 1, 1], "names": ["BaraEllinor", "Killgon", "JoelAuni", "Effa", "glas444", "SofiaTilde2", "CornetTheBunny"]}, {"coords": [11, 5], "value": [1, 6, 2, 1, 4], "names": ["BaraEllinor", "Killgon", "JoelAuni", "Leddy231", "glas444"]}, {"coords": [11, 6], "value": [1, 1, 1, 1, 2, 5, 2, 1], "names": ["BaraEllinor", "Jerua", "Killgon", "JoelAuni", "Effa", "glas444", "Zeffiii", "CornetTheBunny"]}, {"coords": [11, 7], "value": [4, 3, 3, 1, 4, 3, 1], "names": ["Jerua", "JoelAuni", "isahas", "Effa", "glas444", "Zeffiii", "SofiaTilde2"]}, {"coords": [11, 8], "value": [2, 3, 1, 3, 4, 1, 3, 1, 5], "names": ["aggyagnesagi", "Jerua", "KrukPorr", "JoelAuni", "isahas", "wokki10", "glas444", "SofiaTilde2", "lucasdow1"]}, {"coords": [11, 9], "value": [2, 5, 1, 1, 3, 3], "names": ["aggyagnesagi", "isahas", "wokki10", "_gabben", "SofiaTilde2", "lucasdow1"]}, {"coords": [11, 10], "value": [1, 2, 1, 2, 1, 4, 1], "names": ["aggyagnesagi", "wokki10", "glas444", "_gabben", "Tina_T", "SofiaTilde2", "lucasdow1"]}, {"coords": [11, 11], "value": [1, 9, 2, 4], "names": ["aggyagnesagi", "Effa", "wokki10", "_gabben"]}, {"coords": [11, 12], "value": [5, 2, 2], "names": ["Effa", "wokki10", "_gabben"]}, {"coords": [11, 13], "value": [1, 7, 1, 1, 2], "names": ["aggyagnesagi", "isahas", "Effa", "wokki10", "_gabben"]}, {"coords": [11, 14], "value": [2, 1, 1], "names": ["isahas", "Effa", "_gabben"]}, {"coords": [11, 15], "value": [2], "names": ["BaraEllinor"]}, {"coords": [12, 0], "value": [3, 1, 6, 1], "names": ["KrukPorr", "JoelAuni", "CornetTheBunny", "lucasdow1"]}, {"coords": [12, 1], "value": [1, 1, 8, 2], "names": ["BaraEllinor", "JoelAuni", "CornetTheBunny", "lucasdow1"]}, {"coords": [12, 2], "value": [1, 3, 2], "names": ["BaraEllinor", "CornetTheBunny", "lucasdow1"]}, {"coords": [12, 3], "value": [1, 2, 1, 3], "names": ["BaraEllinor", "KrukPorr", "CornetTheBunny", "lucasdow1"]}, {"coords": [12, 4], "value": [1, 1, 1, 1, 2, 3, 4, 1, 1], "names": ["BaraEllinor", "Killgon", "KrukPorr", "JoelAuni", "isahas", "glas444", "SofiaTilde2", "CornetTheBunny", "lucasdow1"]}, {"coords": [12, 5], "value": [1, 3, 3, 3, 10, 4, 1, 1], "names": ["BaraEllinor", "Killgon", "KrukPorr", "isahas", "glas444", "SofiaTilde2", "CornetTheBunny", "lucasdow1"]}, {"coords": [12, 6], "value": [1, 2, 4, 1, 1, 2, 1, 6, 3, 1, 1, 2, 4], "names": ["BaraEllinor", "Jerua", "KrukPorr", "JoelAuni", "isahas", "sfkwww", "Effa", "glas444", "Zeffiii", "Tina_T", "SofiaTilde2", "CornetTheBunny", "lucasdow1"]}, {"coords": [12, 7], "value": [7, 2, 3, 3, 1, 3, 1, 2, 3], "names": ["Jerua", "KrukPorr", "isahas", "sfkwww", "Effa", "glas444", "Zeffiii", "SofiaTilde2", "lucasdow1"]}, {"coords": [12, 8], "value": [6, 1, 3, 2, 1, 1, 4], "names": ["Jerua", "KrukPorr", "isahas", "sfkwww", "Effa", "glas444", "lucasdow1"]}, {"coords": [12, 9], "value": [2, 1, 1, 2, 1, 3, 4], "names": ["Jerua", "isahas", "sfkwww", "Effa", "glas444", "SofiaTilde2", "lucasdow1"]}, {"coords": [12, 10], "value": [1, 1, 2, 1, 1], "names": ["Effa", "glas444", "_gabben", "Tina_T", "SofiaTilde2"]}, {"coords": [12, 11], "value": [8, 4, 4], "names": ["Effa", "glas444", "_gabben"]}, {"coords": [12, 12], "value": [1, 3, 3, 3], "names": ["isahas", "Effa", "glas444", "_gabben"]}, {"coords": [12, 13], "value": [5, 3, 2], "names": ["isahas", "glas444", "_gabben"]}, {"coords": [12, 14], "value": [1, 1], "names": ["Effa", "_gabben"]}, {"coords": [12, 15], "value": [2, 1], "names": ["KrukPorr", "lucasdow1"]}, {"coords": [13, 0], "value": [1, 1, 4], "names": ["KrukPorr", "JoelAuni", "CornetTheBunny"]}, {"coords": [13, 1], "value": [2, 3, 1, 3, 1], "names": ["KrukPorr", "JoelAuni", "glassar", "CornetTheBunny", "lucasdow1"]}, {"coords": [13, 2], "value": [1, 1, 2], "names": ["KrukPorr", "JoelAuni", "CornetTheBunny"]}, {"coords": [13, 3], "value": [3, 1, 2, 1], "names": ["KrukPorr", "glassar", "CornetTheBunny", "lucasdow1"]}, {"coords": [13, 4], "value": [4, 3, 1, 3], "names": ["KrukPorr", "JoelAuni", "glassar", "lucasdow1"]}, {"coords": [13, 5], "value": [3, 1, 1, 1, 2, 2, 2], "names": ["KrukPorr", "isahas", "sfkwww", "glas444", "SofiaTilde2", "CornetTheBunny", "lucasdow1"]}, {"coords": [13, 6], "value": [3, 7, 2, 2, 4, 2, 3, 1, 3, 3], "names": ["Jerua", "KrukPorr", "JoelAuni", "isahas", "sfkwww", "Zeffiii", "Tina_T", "SofiaTilde2", "CornetTheBunny", "lucasdow1"]}, {"coords": [13, 7], "value": [6, 2, 3, 5, 1, 1, 2, 3], "names": ["Jerua", "KrukPorr", "isahas", "sfkwww", "Tina_T", "SofiaTilde2", "CornetTheBunny", "lucasdow1"]}, {"coords": [13, 8], "value": [6, 1, 3, 5, 1, 1, 1], "names": ["Jerua", "KrukPorr", "isahas", "sfkwww", "glas444", "Tina_T", "lucasdow1"]}, {"coords": [13, 9], "value": [5, 1, 2, 3, 1], "names": ["Jerua", "sfkwww", "Effa", "glas444", "lucasdow1"]}, {"coords": [13, 10], "value": [1, 2], "names": ["glas444", "Tina_T"]}, {"coords": [13, 11], "value": [2, 1], "names": ["glas444", "_gabben"]}, {"coords": [13, 12], "value": [5, 7, 3], "names": ["Effa", "glas444", "_gabben"]}, {"coords": [13, 13], "value": [3, 5, 3, 2], "names": ["isahas", "Effa", "glas444", "_gabben"]}, {"coords": [13, 14], "value": [1, 1, 1], "names": ["isahas", "Effa", "_gabben"]}, {"coords": [13, 15], "value": [1, 1], "names": ["_gabben", "lucasdow1"]}, {"coords": [14, 0], "value": [1], "names": ["lucasdow1"]}, {"coords": [14, 1], "value": [2, 2], "names": ["glassar", "lucasdow1"]}, {"coords": [14, 2], "value": [2], "names": ["glassar"]}, {"coords": [14, 3], "value": [3, 3, 1], "names": ["KrukPorr", "glassar", "CornetTheBunny"]}, {"coords": [14, 4], "value": [8, 3, 1, 5], "names": ["KrukPorr", "JoelAuni", "glassar", "CornetTheBunny"]}, {"coords": [14, 5], "value": [4, 4, 1, 1, 3], "names": ["KrukPorr", "JoelAuni", "sfkwww", "Tina_T", "CornetTheBunny"]}, {"coords": [14, 6], "value": [1, 2, 3, 2, 1, 1, 1, 4, 3], "names": ["Jerua", "KrukPorr", "JoelAuni", "isahas", "sfkwww", "marresaurus", "Zeffiii", "Tina_T", "CornetTheBunny"]}, {"coords": [14, 7], "value": [3, 1, 1, 4, 4, 3], "names": ["Jerua", "isahas", "sfkwww", "marresaurus", "Tina_T", "CornetTheBunny"]}, {"coords": [14, 8], "value": [2, 1, 3, 6, 3], "names": ["Jerua", "isahas", "sfkwww", "Tina_T", "CornetTheBunny"]}, {"coords": [14, 9], "value": [3, 1, 1, 2, 1], "names": ["Jerua", "Effa", "glas444", "Tina_T", "CornetTheBunny"]}, {"coords": [14, 10], "value": [1, 1], "names": ["glas444", "Tina_T"]}, {"coords": [14, 11], "value": [], "names": []}, {"coords": [14, 12], "value": [1, 3, 3], "names": ["isahas", "Effa", "glas444"]}, {"coords": [14, 13], "value": [1, 2, 2, 1, 1], "names": ["isahas", "Effa", "glas444", "_gabben", "METALeddy231"]}, {"coords": [14, 14], "value": [1, 1, 3], "names": ["Effa", "_gabben", "METALeddy231"]}, {"coords": [14, 15], "value": [3, 2, 1], "names": ["_gabben", "METALeddy231", "lucasdow1"]}, {"coords": [15, 0], "value": [2, 4], "names": ["_gabben", "lucasdow1"]}, {"coords": [15, 1], "value": [3, 7], "names": ["glassar", "lucasdow1"]}, {"coords": [15, 2], "value": [2, 3], "names": ["glassar", "lucasdow1"]}, {"coords": [15, 3], "value": [3, 2], "names": ["glassar", "lucasdow1"]}, {"coords": [15, 4], "value": [4, 1], "names": ["KrukPorr", "glassar"]}, {"coords": [15, 5], "value": [6, 2, 1, 1], "names": ["KrukPorr", "JoelAuni", "sfkwww", "marresaurus"]}, {"coords": [15, 6], "value": [3, 2, 5, 1], "names": ["KrukPorr", "JoelAuni", "marresaurus", "Zeffiii"]}, {"coords": [15, 7], "value": [1, 1, 6, 2, 3, 1], "names": ["Jerua", "KrukPorr", "marresaurus", "Zeffiii", "Tina_T", "CornetTheBunny"]}, {"coords": [15, 8], "value": [3, 1, 1, 2, 1], "names": ["Jerua", "marresaurus", "Zeffiii", "Tina_T", "CornetTheBunny"]}, {"coords": [15, 9], "value": [6, 3, 2], "names": ["Jerua", "marresaurus", "CornetTheBunny"]}, {"coords": [15, 10], "value": [1], "names": ["Jerua"]}, {"coords": [15, 11], "value": [], "names": []}, {"coords": [15, 12], "value": [], "names": []}, {"coords": [15, 13], "value": [], "names": []}, {"coords": [15, 14], "value": [2], "names": ["_gabben"]}, {"coords": [15, 15], "value": [7, 4, 1], "names": ["_gabben", "METALeddy231", "lucasdow1"]}]